[
  { "id": 1, "bitmap": "0xffffffffffffffff" },
  { "id": 2, "bitmap": "0xf0f0f0f00f0f0f0f" },
  { "id": 3, "bitmap": "0xf0f0f0f0f0f0f0f0" },
  { "id": 4, "bitmap": "0x0f1e1e3c3c7878f0" },
  { "id": 5, "bitmap": "0x3c3c3c3c3c3c3c3c" },
  { "id": 6, "bitmap": "0x0000ffffffff0000" },
  { "id": 7, "bitmap": "0xcccccccccccccccc" },
  { "id": 8, "bitmap": "0x03070f0f0f0f0703" },
  { "id": 9, "bitmap": "0x3c7effffffff7e3c" },
  { "id": 10, "bitmap": "0x3377ffffffff7733" },
  { "id": 11, "bitmap": "0x3333cccc3333cccc" },
  { "id": 12, "bitmap": "0xc0e0f0f0f0f0e0c0" },
  { "id": 13, "bitmap": "0xcceeffffffffeecc" },
  { "id": 14, "bitmap": "0x0000ffff0000ffff" },
  { "id": 15, "bitmap": "0x00000000ffffffff" },
  { "id": 16, "bitmap": "0xfc8282fc828282fc" },
  { "id": 17, "bitmap": "0x7c8282fe82828282" },
  { "id": 18, "bitmap": "0xfe10101010101010" },
  { "id": 19, "bitmap": "0x7e8080808080807e" },
  { "id": 20, "bitmap": "0x828282fe82828282" },
  { "id": 21, "bitmap": "0x7e80807e8080807e" },
  { "id": 22, "bitmap": "0x7e80807c020202fc" },
  { "id": 23, "bitmap": "0xfec3c3fec3c3c3fe" },
  { "id": 24, "bitmap": "0x7ec3c3ffc3c3c3c3" },
  { "id": 25, "bitmap": "0xff18181818181818" },
  { "id": 26, "bitmap": "0x7ec3c0c0c0c0c37e" },
  { "id": 27, "bitmap": "0xc3c3c3ffc3c3c3c3" },
  { "id": 28, "bitmap": "0xffc0c0fec0c0c0ff" },
  { "id": 29, "bitmap": "0x7ec3c07e0303c37e" },
  { "id": 30, "bitmap": "0xfeffe7fefee7fffe" },
  { "id": 31, "bitmap": "0x7effe7e7ffffe7e7" },
  { "id": 32, "bitmap": "0xffff3c3c3c3c3c3c" },
  { "id": 33, "bitmap": "0x7effe7e0e0e7ff7e" },
  { "id": 34, "bitmap": "0xe7e7e7ffffe7e7e7" },
  { "id": 35, "bitmap": "0x7fffe0f8f8e0ff7f" },
  { "id": 36, "bitmap": "0x7effe0fe7f07ff7e" },
  { "id": 37, "bitmap": "0xfcfcecfefeeefefe" },
  { "id": 38, "bitmap": "0xfefefeeefefeeeee" },
  { "id": 39, "bitmap": "0xfefefefe38383838" },
  { "id": 40, "bitmap": "0xfefefee0e0fefefe" },
  { "id": 41, "bitmap": "0xeeeefefefefeeeee" },
  { "id": 42, "bitmap": "0xfefee0f8e0fefefe" },
  { "id": 43, "bitmap": "0xfefee0fefe0efefe" },
  { "id": 44, "bitmap": "0xfc8282fc868386fc" },
  { "id": 45, "bitmap": "0x181824247e42c381" },
  { "id": 46, "bitmap": "0xff99181818181818" },
  { "id": 47, "bitmap": "0x1e6380808080631e" },
  { "id": 48, "bitmap": "0xc38181ff818181c3" },
  { "id": 49, "bitmap": "0x7e8290f0f090827e" },
  { "id": 50, "bitmap": "0x7e8180700e81817e" },
  { "id": 51, "bitmap": "0xfcc2c2ffe1e1e1ff" },
  { "id": 52, "bitmap": "0xfcc2c2c1ffe1e1e1" },
  { "id": 53, "bitmap": "0xff1818181c1c1c1c" },
  { "id": 54, "bitmap": "0xfec2c0c0e0e0e1ff" },
  { "id": 55, "bitmap": "0xc2c2c2ffe1e1e1e1" },
  { "id": 56, "bitmap": "0xfcc0c0f8e0e0e0ff" },
  { "id": 57, "bitmap": "0x7fc1c0ff030383fe" },
  { "id": 58, "bitmap": "0xfe63637e636363fe" },
  { "id": 59, "bitmap": "0x18181c2c2e7e47c7" },
  { "id": 60, "bitmap": "0x7edb18181818183c" },
  { "id": 61, "bitmap": "0x3e6383808083633e" },
  { "id": 62, "bitmap": "0xef66667e7e6666f7" },
  { "id": 63, "bitmap": "0xfe63607c646063fe" },
  { "id": 64, "bitmap": "0x7cc3c3781e07c77e" },
  { "id": 65, "bitmap": "0x7c8299829999827c" },
  { "id": 66, "bitmap": "0x3c42999981999966" },
  { "id": 67, "bitmap": "0x7e81662424242418" },
  { "id": 68, "bitmap": "0x3e419e90909e413e" },
  { "id": 69, "bitmap": "0x6699998199999966" },
  { "id": 70, "bitmap": "0x7e819e829c9e817e" },
  { "id": 71, "bitmap": "0x3e418e423979827c" },
  { "id": 72, "bitmap": "0x3f7f73fffff3ffff" },
  { "id": 73, "bitmap": "0x1f7f73f3fffff3f3" },
  { "id": 74, "bitmap": "0xffffff3c3c3c3c3c" },
  { "id": 75, "bitmap": "0x1f7f73f3f0f0ffff" },
  { "id": 76, "bitmap": "0xf3f3f3fffff3f3f3" },
  { "id": 77, "bitmap": "0x1f7f70fcfcf0ffff" },
  { "id": 78, "bitmap": "0x3f7f70ffff0fffff" }
]